WinTunnel-0.0.2.dist-info/DESCRIPTION.rst
WinTunnel-0.0.2.dist-info/METADATA
WinTunnel-0.0.2.dist-info/RECORD
WinTunnel-0.0.2.dist-info/WHEEL
WinTunnel-0.0.2.dist-info/dependency_links.txt
WinTunnel-0.0.2.dist-info/entry_points.txt
WinTunnel-0.0.2.dist-info/metadata.json
WinTunnel-0.0.2.dist-info/top_level.txt
wintunnel/__init__.py
wintunnel/__main__.py
wintunnel/main.py
wintunnel/smb_tunnel.py
wintunnel/winrm_tunnel.py
